{"id": 592663, "fullName": "J.T. Realmuto", "link": "/api/v1/people/592663", "firstName": "Jacob", "lastName": "Realmuto", "primaryNumber": "10", "birthDate": "1991-03-18", "currentAge": 33, "birthCity": "Del City", "birthStateProvince": "OK", "birthCountry": "USA", "height": "6' 1\"", "weight": 212, "active": true, "primaryPosition": {"code": "2", "name": "Catcher", "type": "Catcher", "abbreviation": "C"}, "useName": "J.T.", "useLastName": "Realmuto", "middleName": "Tyler", "boxscoreName": "Realmuto", "nickName": "Real", "gender": "M", "isPlayer": true, "isVerified": true, "draftYear": 2010, "pronunciation": "reel-MYOO-toh", "stats": [{"type": {"displayName": "byDateRange"}, "group": {"displayName": "hitting"}, "exemptions": [], "splits": [{"stat": {"gamesPlayed": 16, "flyOuts": 5, "groundOuts": 12, "airOuts": 13, "runs": 9, "doubles": 0, "triples": 0, "homeRuns": 3, "strikeOuts": 20, "baseOnBalls": 4, "intentionalWalks": 0, "hits": 16, "hitByPitch": 0, "avg": ".262", "atBats": 61, "obp": ".308", "slg": ".410", "ops": ".718", "caughtStealing": 1, "stolenBases": 0, "stolenBasePercentage": ".000", "groundIntoDoublePlay": 0, "groundIntoTriplePlay": 0, "numberOfPitches": 264, "plateAppearances": 65, "totalBases": 25, "rbi": 7, "leftOnBase": 26, "sacBunts": 0, "sacFlies": 0, "babip": ".342", "groundOutsToAirouts": "0.92", "catchersInterference": 0, "atBatsPerHomeRun": "20.33"}, "team": {"id": 143, "name": "Philadelphia Phillies", "link": "/api/v1/teams/143"}, "sport": {"id": 1, "link": "/api/v1/sports/1", "abbreviation": "MLB"}, "numTeams": 1, "numLeagues": 16}, {"stat": {"gamesPlayed": 16, "flyOuts": 5, "groundOuts": 12, "airOuts": 13, "runs": 9, "doubles": 0, "triples": 0, "homeRuns": 3, "strikeOuts": 20, "baseOnBalls": 4, "intentionalWalks": 0, "hits": 16, "hitByPitch": 0, "avg": ".262", "atBats": 61, "obp": ".308", "slg": ".410", "ops": ".718", "caughtStealing": 1, "stolenBases": 0, "stolenBasePercentage": ".000", "groundIntoDoublePlay": 0, "groundIntoTriplePlay": 0, "numberOfPitches": 264, "plateAppearances": 65, "totalBases": 25, "rbi": 7, "leftOnBase": 26, "sacBunts": 0, "sacFlies": 0, "babip": ".342", "groundOutsToAirouts": "0.92", "catchersInterference": 0, "atBatsPerHomeRun": "20.33"}, "team": {"id": 143, "name": "Philadelphia Phillies", "link": "/api/v1/teams/143"}, "sport": {"id": 0, "link": "/api/v1/sports/0", "abbreviation": "All"}, "numTeams": 1, "numLeagues": 16}]}], "mlbDebutDate": "2014-06-05", "batSide": {"code": "R", "description": "Right"}, "pitchHand": {"code": "R", "description": "Right"}, "nameFirstLast": "J.T. Realmuto", "nameSlug": "j-t-realmuto-592663", "firstLastName": "J.T. Realmuto", "lastFirstName": "Realmuto, J.T.", "lastInitName": "Realmuto, J", "initLastName": "J Realmuto", "fullFMLName": "Jacob Tyler Realmuto", "fullLFMName": "Realmuto, Jacob Tyler", "strikeZoneTop": 3.71, "strikeZoneBottom": 1.76}