[{"game_id": 745361, "game_datetime": "2024-04-05T20:35:00Z", "game_date": "2024-04-05", "game_type": "R", "status": "Final", "away_name": "San Diego Padres", "home_name": "San Francisco Giants", "away_id": 135, "home_id": 137, "doubleheader": "N", "game_num": 1, "home_probable_pitcher": "Jordan Hicks", "away_probable_pitcher": "Dylan Cease", "home_pitcher_note": "", "away_pitcher_note": "", "away_score": 2, "home_score": 3, "current_inning": 9, "inning_state": "Bottom", "venue_id": 2395, "venue_name": "Oracle Park", "national_broadcasts": [], "series_status": null, "winning_team": "San Francisco Giants", "losing_team": "San Diego Padres", "winning_pitcher": "Camilo Doval", "losing_pitcher": "Enyel De Los Santos", "save_pitcher": null, "summary": "2024-04-05 - San Diego Padres (2) @ San Francisco Giants (3) (Final)"}]