{"id": 701538, "fullName": "Jackson Merrill", "link": "/api/v1/people/701538", "firstName": "Jackson", "lastName": "Merrill", "primaryNumber": "3", "birthDate": "2003-04-19", "currentAge": 21, "birthCity": "Baltimore", "birthStateProvince": "MD", "birthCountry": "USA", "height": "6' 3\"", "weight": 195, "active": true, "primaryPosition": {"code": "8", "name": "Outfielder", "type": "Outfielder", "abbreviation": "CF"}, "useName": "Jackson", "useLastName": "Merrill", "middleName": "Peter", "boxscoreName": "Merrill", "gender": "M", "isPlayer": true, "isVerified": true, "draftYear": 2021, "stats": [{"type": {"displayName": "byDateRange"}, "group": {"displayName": "hitting"}, "exemptions": [], "splits": [{"stat": {"gamesPlayed": 28, "flyOuts": 20, "groundOuts": 19, "airOuts": 28, "runs": 12, "doubles": 3, "triples": 1, "homeRuns": 1, "strikeOuts": 17, "baseOnBalls": 9, "intentionalWalks": 1, "hits": 28, "hitByPitch": 0, "avg": ".308", "atBats": 91, "obp": ".366", "slg": ".396", "ops": ".762", "caughtStealing": 2, "stolenBases": 4, "stolenBasePercentage": ".667", "groundIntoDoublePlay": 0, "groundIntoTriplePlay": 0, "numberOfPitches": 371, "plateAppearances": 101, "totalBases": 36, "rbi": 12, "leftOnBase": 42, "sacBunts": 0, "sacFlies": 1, "babip": ".365", "groundOutsToAirouts": "0.68", "catchersInterference": 0, "atBatsPerHomeRun": "91.00"}, "team": {"id": 135, "name": "San Diego Padres", "link": "/api/v1/teams/135"}, "sport": {"id": 1, "link": "/api/v1/sports/1", "abbreviation": "MLB"}, "numTeams": 1, "numLeagues": 28}, {"stat": {"gamesPlayed": 28, "flyOuts": 20, "groundOuts": 19, "airOuts": 28, "runs": 12, "doubles": 3, "triples": 1, "homeRuns": 1, "strikeOuts": 17, "baseOnBalls": 9, "intentionalWalks": 1, "hits": 28, "hitByPitch": 0, "avg": ".308", "atBats": 91, "obp": ".366", "slg": ".396", "ops": ".762", "caughtStealing": 2, "stolenBases": 4, "stolenBasePercentage": ".667", "groundIntoDoublePlay": 0, "groundIntoTriplePlay": 0, "numberOfPitches": 371, "plateAppearances": 101, "totalBases": 36, "rbi": 12, "leftOnBase": 42, "sacBunts": 0, "sacFlies": 1, "babip": ".365", "groundOutsToAirouts": "0.68", "catchersInterference": 0, "atBatsPerHomeRun": "91.00"}, "team": {"id": 135, "name": "San Diego Padres", "link": "/api/v1/teams/135"}, "sport": {"id": 0, "link": "/api/v1/sports/0", "abbreviation": "All"}, "numTeams": 1, "numLeagues": 28}]}], "mlbDebutDate": "2024-03-20", "batSide": {"code": "L", "description": "Left"}, "pitchHand": {"code": "R", "description": "Right"}, "nameFirstLast": "Jackson Merrill", "nameSlug": "jackson-merrill-701538", "firstLastName": "Jackson Merrill", "lastFirstName": "Merrill, Jackson", "lastInitName": "Merrill, J", "initLastName": "J Merrill", "fullFMLName": "Jackson Peter Merrill", "fullLFMName": "Merrill, Jackson Peter", "strikeZoneTop": 3.49, "strikeZoneBottom": 1.62}