{"id": 650489, "fullName": "Willi Castro", "link": "/api/v1/people/650489", "firstName": "Willi", "lastName": "Castro", "primaryNumber": "50", "birthDate": "1997-04-24", "currentAge": 27, "birthCity": "Rio Piedras", "birthCountry": "Puerto Rico", "height": "6' 1\"", "weight": 206, "active": true, "primaryPosition": {"code": "6", "name": "Shortstop", "type": "Infielder", "abbreviation": "SS"}, "useName": "Willi", "useLastName": "Castro", "middleName": "Rafael", "boxscoreName": "Castro, W", "gender": "M", "nameMatrilineal": "Capellan", "isPlayer": true, "isVerified": false, "pronunciation": "willie", "stats": [{"type": {"displayName": "byDateRange"}, "group": {"displayName": "hitting"}, "exemptions": [], "splits": [{"stat": {"gamesPlayed": 47, "flyOuts": 19, "groundOuts": 35, "airOuts": 40, "runs": 21, "doubles": 11, "triples": 3, "homeRuns": 3, "strikeOuts": 45, "baseOnBalls": 11, "intentionalWalks": 0, "hits": 43, "hitByPitch": 3, "avg": ".265", "atBats": 162, "obp": ".322", "slg": ".426", "ops": ".748", "caughtStealing": 4, "stolenBases": 6, "stolenBasePercentage": ".600", "groundIntoDoublePlay": 2, "groundIntoTriplePlay": 0, "numberOfPitches": 683, "plateAppearances": 177, "totalBases": 69, "rbi": 14, "leftOnBase": 86, "sacBunts": 0, "sacFlies": 1, "babip": ".348", "groundOutsToAirouts": "0.88", "catchersInterference": 0, "atBatsPerHomeRun": "54.00"}, "team": {"id": 142, "name": "Minnesota Twins", "link": "/api/v1/teams/142"}, "sport": {"id": 1, "link": "/api/v1/sports/1", "abbreviation": "MLB"}, "numTeams": 1, "numLeagues": 47}, {"stat": {"gamesPlayed": 47, "flyOuts": 19, "groundOuts": 35, "airOuts": 40, "runs": 21, "doubles": 11, "triples": 3, "homeRuns": 3, "strikeOuts": 45, "baseOnBalls": 11, "intentionalWalks": 0, "hits": 43, "hitByPitch": 3, "avg": ".265", "atBats": 162, "obp": ".322", "slg": ".426", "ops": ".748", "caughtStealing": 4, "stolenBases": 6, "stolenBasePercentage": ".600", "groundIntoDoublePlay": 2, "groundIntoTriplePlay": 0, "numberOfPitches": 683, "plateAppearances": 177, "totalBases": 69, "rbi": 14, "leftOnBase": 86, "sacBunts": 0, "sacFlies": 1, "babip": ".348", "groundOutsToAirouts": "0.88", "catchersInterference": 0, "atBatsPerHomeRun": "54.00"}, "team": {"id": 142, "name": "Minnesota Twins", "link": "/api/v1/teams/142"}, "sport": {"id": 0, "link": "/api/v1/sports/0", "abbreviation": "All"}, "numTeams": 1, "numLeagues": 47}]}], "mlbDebutDate": "2019-08-24", "batSide": {"code": "S", "description": "Switch"}, "pitchHand": {"code": "R", "description": "Right"}, "nameFirstLast": "Willi Castro", "nameSlug": "willi-castro-650489", "firstLastName": "Willi Castro", "lastFirstName": "Castro, Willi", "lastInitName": "Castro, W", "initLastName": "W Castro", "fullFMLName": "Willi Rafael Castro", "fullLFMName": "Castro, Willi Rafael", "strikeZoneTop": 3.53, "strikeZoneBottom": 1.69}