{"id": 665833, "fullName": "Oneil Cruz", "link": "/api/v1/people/665833", "firstName": "Oneil", "lastName": "Cruz", "primaryNumber": "15", "birthDate": "1998-10-04", "currentAge": 26, "birthCity": "Nizao", "birthCountry": "Dominican Republic", "height": "6' 7\"", "weight": 215, "active": true, "primaryPosition": {"code": "6", "name": "Shortstop", "type": "Infielder", "abbreviation": "SS"}, "useName": "Oneil", "useLastName": "Cruz", "boxscoreName": "Cruz, O", "gender": "M", "nameMatrilineal": "Urena", "isPlayer": true, "isVerified": false, "stats": [{"type": {"displayName": "byDateRange"}, "group": {"displayName": "hitting"}, "exemptions": [], "splits": [{"stat": {"gamesPlayed": 17, "flyOuts": 4, "groundOuts": 17, "airOuts": 7, "runs": 8, "doubles": 1, "triples": 0, "homeRuns": 3, "strikeOuts": 29, "baseOnBalls": 4, "intentionalWalks": 1, "hits": 16, "hitByPitch": 0, "avg": ".232", "atBats": 69, "obp": ".274", "slg": ".377", "ops": ".651", "caughtStealing": 0, "stolenBases": 1, "stolenBasePercentage": "1.000", "groundIntoDoublePlay": 2, "groundIntoTriplePlay": 0, "numberOfPitches": 303, "plateAppearances": 73, "totalBases": 26, "rbi": 6, "leftOnBase": 40, "sacBunts": 0, "sacFlies": 0, "babip": ".351", "groundOutsToAirouts": "2.43", "catchersInterference": 0, "atBatsPerHomeRun": "23.00"}, "team": {"id": 134, "name": "Pittsburgh Pirates", "link": "/api/v1/teams/134"}, "sport": {"id": 1, "link": "/api/v1/sports/1", "abbreviation": "MLB"}, "numTeams": 1, "numLeagues": 17}, {"stat": {"gamesPlayed": 17, "flyOuts": 4, "groundOuts": 17, "airOuts": 7, "runs": 8, "doubles": 1, "triples": 0, "homeRuns": 3, "strikeOuts": 29, "baseOnBalls": 4, "intentionalWalks": 1, "hits": 16, "hitByPitch": 0, "avg": ".232", "atBats": 69, "obp": ".274", "slg": ".377", "ops": ".651", "caughtStealing": 0, "stolenBases": 1, "stolenBasePercentage": "1.000", "groundIntoDoublePlay": 2, "groundIntoTriplePlay": 0, "numberOfPitches": 303, "plateAppearances": 73, "totalBases": 26, "rbi": 6, "leftOnBase": 40, "sacBunts": 0, "sacFlies": 0, "babip": ".351", "groundOutsToAirouts": "2.43", "catchersInterference": 0, "atBatsPerHomeRun": "23.00"}, "team": {"id": 134, "name": "Pittsburgh Pirates", "link": "/api/v1/teams/134"}, "sport": {"id": 0, "link": "/api/v1/sports/0", "abbreviation": "All"}, "numTeams": 1, "numLeagues": 17}]}], "mlbDebutDate": "2021-10-02", "batSide": {"code": "L", "description": "Left"}, "pitchHand": {"code": "R", "description": "Right"}, "nameFirstLast": "Oneil Cruz", "nameSlug": "oneil-cruz-665833", "firstLastName": "Oneil Cruz", "lastFirstName": "Cruz, Oneil", "lastInitName": "Cruz, O", "initLastName": "O Cruz", "fullFMLName": "Oneil Cruz", "fullLFMName": "Cruz, Oneil", "strikeZoneTop": 3.82, "strikeZoneBottom": 1.81}