{"id": 663586, "fullName": "Austin Riley", "link": "/api/v1/people/663586", "firstName": "Michael", "lastName": "Riley", "primaryNumber": "27", "birthDate": "1997-04-02", "currentAge": 27, "birthCity": "Memphis", "birthStateProvince": "TN", "birthCountry": "USA", "height": "6' 3\"", "weight": 240, "active": true, "primaryPosition": {"code": "5", "name": "Third Base", "type": "Infielder", "abbreviation": "3B"}, "useName": "Austin", "useLastName": "Riley", "middleName": "Austin", "boxscoreName": "Riley, A", "nickName": "Ocho", "gender": "M", "isPlayer": true, "isVerified": true, "draftYear": 2015, "stats": [{"type": {"displayName": "byDateRange"}, "group": {"displayName": "hitting"}, "exemptions": [], "splits": [{"stat": {"gamesPlayed": 8, "flyOuts": 3, "groundOuts": 9, "airOuts": 6, "runs": 8, "doubles": 3, "triples": 0, "homeRuns": 2, "strikeOuts": 11, "baseOnBalls": 2, "intentionalWalks": 0, "hits": 9, "hitByPitch": 0, "avg": ".257", "atBats": 35, "obp": ".297", "slg": ".514", "ops": ".811", "caughtStealing": 0, "stolenBases": 0, "stolenBasePercentage": ".---", "groundIntoDoublePlay": 1, "groundIntoTriplePlay": 0, "numberOfPitches": 131, "plateAppearances": 37, "totalBases": 18, "rbi": 8, "leftOnBase": 16, "sacBunts": 0, "sacFlies": 0, "babip": ".318", "groundOutsToAirouts": "1.50", "catchersInterference": 0, "atBatsPerHomeRun": "17.50"}, "team": {"id": 144, "name": "Atlanta Braves", "link": "/api/v1/teams/144"}, "sport": {"id": 1, "link": "/api/v1/sports/1", "abbreviation": "MLB"}, "numTeams": 1, "numLeagues": 8}, {"stat": {"gamesPlayed": 8, "flyOuts": 3, "groundOuts": 9, "airOuts": 6, "runs": 8, "doubles": 3, "triples": 0, "homeRuns": 2, "strikeOuts": 11, "baseOnBalls": 2, "intentionalWalks": 0, "hits": 9, "hitByPitch": 0, "avg": ".257", "atBats": 35, "obp": ".297", "slg": ".514", "ops": ".811", "caughtStealing": 0, "stolenBases": 0, "stolenBasePercentage": ".---", "groundIntoDoublePlay": 1, "groundIntoTriplePlay": 0, "numberOfPitches": 131, "plateAppearances": 37, "totalBases": 18, "rbi": 8, "leftOnBase": 16, "sacBunts": 0, "sacFlies": 0, "babip": ".318", "groundOutsToAirouts": "1.50", "catchersInterference": 0, "atBatsPerHomeRun": "17.50"}, "team": {"id": 144, "name": "Atlanta Braves", "link": "/api/v1/teams/144"}, "sport": {"id": 0, "link": "/api/v1/sports/0", "abbreviation": "All"}, "numTeams": 1, "numLeagues": 8}]}], "mlbDebutDate": "2019-05-15", "batSide": {"code": "R", "description": "Right"}, "pitchHand": {"code": "R", "description": "Right"}, "nameFirstLast": "Austin Riley", "nameSlug": "austin-riley-663586", "firstLastName": "Austin Riley", "lastFirstName": "Riley, Austin", "lastInitName": "Riley, A", "initLastName": "A Riley", "fullFMLName": "Michael Austin Riley", "fullLFMName": "Riley, Michael Austin", "strikeZoneTop": 3.45, "strikeZoneBottom": 1.61}