[{"game_id": 745578, "game_datetime": "2024-05-21T22:40:00Z", "game_date": "2024-05-21", "game_type": "R", "status": "Final", "away_name": "Texas Rangers", "home_name": "Philadelphia Phillies", "away_id": 140, "home_id": 143, "doubleheader": "N", "game_num": 1, "home_probable_pitcher": "Ranger Su\u00e1rez", "away_probable_pitcher": "Jon Gray", "home_pitcher_note": "", "away_pitcher_note": "", "away_score": 2, "home_score": 5, "current_inning": 9, "inning_state": "Top", "venue_id": 2681, "venue_name": "Citizens Bank Park", "national_broadcasts": [], "series_status": null, "winning_team": "Philadelphia Phillies", "losing_team": "Texas Rangers", "winning_pitcher": "Ranger Su\u00e1rez", "losing_pitcher": "Jon Gray", "save_pitcher": "Jos\u00e9 Alvarado", "summary": "2024-05-21 - Texas Rangers (2) @ Philadelphia Phillies (5) (Final)"}, {"game_id": 745576, "game_datetime": "2024-05-22T22:40:00Z", "game_date": "2024-05-22", "game_type": "R", "status": "Final", "away_name": "Texas Rangers", "home_name": "Philadelphia Phillies", "away_id": 140, "home_id": 143, "doubleheader": "N", "game_num": 1, "home_probable_pitcher": "Taijuan Walker", "away_probable_pitcher": "Dane Dunning", "home_pitcher_note": "", "away_pitcher_note": "", "away_score": 4, "home_score": 11, "current_inning": 9, "inning_state": "Top", "venue_id": 2681, "venue_name": "Citizens Bank Park", "national_broadcasts": ["MLBN (out-of-market only)"], "series_status": null, "winning_team": "Philadelphia Phillies", "losing_team": "Texas Rangers", "winning_pitcher": "Matt Strahm", "losing_pitcher": "Dane Dunning", "save_pitcher": null, "summary": "2024-05-22 - Texas Rangers (4) @ Philadelphia Phillies (11) (Final)"}]