{"id": 677960, "fullName": "Ryan Weathers", "link": "/api/v1/people/677960", "firstName": "Ryan", "lastName": "Weathers", "primaryNumber": "60", "birthDate": "1999-12-17", "currentAge": 24, "birthCity": "Loretto", "birthStateProvince": "TN", "birthCountry": "USA", "height": "6' 1\"", "weight": 230, "active": true, "primaryPosition": {"code": "1", "name": "Pitcher", "type": "Pitcher", "abbreviation": "P"}, "useName": "Ryan", "useLastName": "Weathers", "boxscoreName": "Weathers", "gender": "M", "isPlayer": true, "isVerified": false, "draftYear": 2018, "stats": [{"type": {"displayName": "byDateRange"}, "group": {"displayName": "pitching"}, "exemptions": [], "splits": [{"stat": {"gamesPlayed": 2, "gamesStarted": 2, "flyOuts": 4, "groundOuts": 8, "airOuts": 8, "runs": 6, "doubles": 3, "triples": 0, "homeRuns": 1, "strikeOuts": 11, "baseOnBalls": 5, "intentionalWalks": 0, "hits": 10, "hitByPitch": 3, "avg": ".270", "atBats": 37, "obp": ".400", "slg": ".432", "ops": ".832", "caughtStealing": 0, "stolenBases": 0, "stolenBasePercentage": ".---", "groundIntoDoublePlay": 1, "numberOfPitches": 179, "era": "4.00", "inningsPitched": "9.0", "wins": 0, "losses": 1, "saves": 0, "saveOpportunities": 0, "holds": 0, "blownSaves": 0, "earnedRuns": 4, "whip": "1.67", "battersFaced": 45, "outs": 27, "gamesPitched": 2, "completeGames": 0, "shutouts": 0, "strikes": 107, "strikePercentage": ".600", "hitBatsmen": 3, "balks": 0, "wildPitches": 1, "pickoffs": 0, "totalBases": 16, "groundOutsToAirouts": "1.00", "winPercentage": ".000", "pitchesPerInning": "19.89", "gamesFinished": 0, "strikeoutWalkRatio": "2.20", "strikeoutsPer9Inn": "11.00", "walksPer9Inn": "5.00", "hitsPer9Inn": "10.00", "runsScoredPer9": "6.00", "homeRunsPer9": "1.00", "inheritedRunners": 0, "inheritedRunnersScored": 0, "catchersInterference": 0, "sacBunts": 0, "sacFlies": 0}, "team": {"id": 146, "name": "Miami Marlins", "link": "/api/v1/teams/146"}, "sport": {"id": 1, "link": "/api/v1/sports/1", "abbreviation": "MLB"}, "numTeams": 1, "numLeagues": 2}, {"stat": {"gamesPlayed": 2, "gamesStarted": 2, "flyOuts": 4, "groundOuts": 8, "airOuts": 8, "runs": 6, "doubles": 3, "triples": 0, "homeRuns": 1, "strikeOuts": 11, "baseOnBalls": 5, "intentionalWalks": 0, "hits": 10, "hitByPitch": 3, "avg": ".270", "atBats": 37, "obp": ".400", "slg": ".432", "ops": ".832", "caughtStealing": 0, "stolenBases": 0, "stolenBasePercentage": ".---", "groundIntoDoublePlay": 1, "numberOfPitches": 179, "era": "4.00", "inningsPitched": "9.0", "wins": 0, "losses": 1, "saves": 0, "saveOpportunities": 0, "holds": 0, "blownSaves": 0, "earnedRuns": 4, "whip": "1.67", "battersFaced": 45, "outs": 27, "gamesPitched": 2, "completeGames": 0, "shutouts": 0, "strikes": 107, "strikePercentage": ".600", "hitBatsmen": 3, "balks": 0, "wildPitches": 1, "pickoffs": 0, "totalBases": 16, "groundOutsToAirouts": "1.00", "winPercentage": ".000", "pitchesPerInning": "19.89", "gamesFinished": 0, "strikeoutWalkRatio": "2.20", "strikeoutsPer9Inn": "11.00", "walksPer9Inn": "5.00", "hitsPer9Inn": "10.00", "runsScoredPer9": "6.00", "homeRunsPer9": "1.00", "inheritedRunners": 0, "inheritedRunnersScored": 0, "catchersInterference": 0, "sacBunts": 0, "sacFlies": 0}, "team": {"id": 146, "name": "Miami Marlins", "link": "/api/v1/teams/146"}, "sport": {"id": 0, "link": "/api/v1/sports/0", "abbreviation": "All"}, "numTeams": 1, "numLeagues": 2}]}], "mlbDebutDate": "2020-10-06", "batSide": {"code": "R", "description": "Right"}, "pitchHand": {"code": "L", "description": "Left"}, "nameFirstLast": "Ryan Weathers", "nameSlug": "ryan-weathers-677960", "firstLastName": "Ryan Weathers", "lastFirstName": "Weathers, Ryan", "lastInitName": "Weathers, R", "initLastName": "R Weathers", "fullFMLName": "Ryan  Weathers", "fullLFMName": "Weathers, Ryan", "strikeZoneTop": 3.411, "strikeZoneBottom": 1.565}