{"id": 669203, "fullName": "Corbin Burnes", "link": "/api/v1/people/669203", "firstName": "Corbin", "lastName": "Burnes", "primaryNumber": "39", "birthDate": "1994-10-22", "currentAge": 30, "birthCity": "Bakersfield", "birthStateProvince": "CA", "birthCountry": "USA", "height": "6' 3\"", "weight": 245, "active": true, "primaryPosition": {"code": "1", "name": "Pitcher", "type": "Pitcher", "abbreviation": "P"}, "useName": "Corbin", "useLastName": "Burnes", "middleName": "Brian", "boxscoreName": "Burnes", "nickName": "Burnesy", "gender": "M", "isPlayer": true, "isVerified": false, "draftYear": 2016, "stats": [{"type": {"displayName": "byDateRange"}, "group": {"displayName": "pitching"}, "exemptions": [], "splits": [{"stat": {"gamesPlayed": 13, "gamesStarted": 13, "flyOuts": 35, "groundOuts": 81, "airOuts": 76, "runs": 23, "doubles": 9, "triples": 0, "homeRuns": 7, "strikeOuts": 76, "baseOnBalls": 21, "intentionalWalks": 0, "hits": 60, "hitByPitch": 0, "avg": ".205", "atBats": 293, "obp": ".258", "slg": ".307", "ops": ".565", "caughtStealing": 3, "stolenBases": 15, "stolenBasePercentage": ".833", "groundIntoDoublePlay": 3, "numberOfPitches": 1233, "era": "2.26", "inningsPitched": "79.2", "wins": 6, "losses": 2, "saves": 0, "saveOpportunities": 0, "holds": 0, "blownSaves": 0, "earnedRuns": 20, "whip": "1.02", "battersFaced": 314, "outs": 239, "gamesPitched": 13, "completeGames": 0, "shutouts": 0, "strikes": 803, "strikePercentage": ".650", "hitBatsmen": 0, "balks": 2, "wildPitches": 2, "pickoffs": 2, "totalBases": 90, "groundOutsToAirouts": "1.07", "winPercentage": ".750", "pitchesPerInning": "15.48", "gamesFinished": 0, "strikeoutWalkRatio": "3.62", "strikeoutsPer9Inn": "8.59", "walksPer9Inn": "2.37", "hitsPer9Inn": "6.78", "runsScoredPer9": "2.60", "homeRunsPer9": "0.79", "inheritedRunners": 0, "inheritedRunnersScored": 0, "catchersInterference": 0, "sacBunts": 0, "sacFlies": 0}, "team": {"id": 110, "name": "Baltimore Orioles", "link": "/api/v1/teams/110"}, "sport": {"id": 1, "link": "/api/v1/sports/1", "abbreviation": "MLB"}, "numTeams": 1, "numLeagues": 13}, {"stat": {"gamesPlayed": 13, "gamesStarted": 13, "flyOuts": 35, "groundOuts": 81, "airOuts": 76, "runs": 23, "doubles": 9, "triples": 0, "homeRuns": 7, "strikeOuts": 76, "baseOnBalls": 21, "intentionalWalks": 0, "hits": 60, "hitByPitch": 0, "avg": ".205", "atBats": 293, "obp": ".258", "slg": ".307", "ops": ".565", "caughtStealing": 3, "stolenBases": 15, "stolenBasePercentage": ".833", "groundIntoDoublePlay": 3, "numberOfPitches": 1233, "era": "2.26", "inningsPitched": "79.2", "wins": 6, "losses": 2, "saves": 0, "saveOpportunities": 0, "holds": 0, "blownSaves": 0, "earnedRuns": 20, "whip": "1.02", "battersFaced": 314, "outs": 239, "gamesPitched": 13, "completeGames": 0, "shutouts": 0, "strikes": 803, "strikePercentage": ".650", "hitBatsmen": 0, "balks": 2, "wildPitches": 2, "pickoffs": 2, "totalBases": 90, "groundOutsToAirouts": "1.07", "winPercentage": ".750", "pitchesPerInning": "15.48", "gamesFinished": 0, "strikeoutWalkRatio": "3.62", "strikeoutsPer9Inn": "8.59", "walksPer9Inn": "2.37", "hitsPer9Inn": "6.78", "runsScoredPer9": "2.60", "homeRunsPer9": "0.79", "inheritedRunners": 0, "inheritedRunnersScored": 0, "catchersInterference": 0, "sacBunts": 0, "sacFlies": 0}, "team": {"id": 110, "name": "Baltimore Orioles", "link": "/api/v1/teams/110"}, "sport": {"id": 0, "link": "/api/v1/sports/0", "abbreviation": "All"}, "numTeams": 1, "numLeagues": 13}]}], "mlbDebutDate": "2018-07-10", "batSide": {"code": "R", "description": "Right"}, "pitchHand": {"code": "R", "description": "Right"}, "nameFirstLast": "Corbin Burnes", "nameSlug": "corbin-burnes-669203", "firstLastName": "Corbin Burnes", "lastFirstName": "Burnes, Corbin", "lastInitName": "Burnes, C", "initLastName": "C Burnes", "fullFMLName": "Corbin Brian Burnes", "fullLFMName": "Burnes, Corbin Brian", "strikeZoneTop": 3.49, "strikeZoneBottom": 1.66}