{"id": 680869, "fullName": "Zack Gelof", "link": "/api/v1/people/680869", "firstName": "Zachary", "lastName": "Gelof", "primaryNumber": "20", "birthDate": "1999-10-19", "currentAge": 25, "birthCity": "Rehoboth Beach", "birthStateProvince": "DE", "birthCountry": "USA", "height": "6' 2\"", "weight": 205, "active": true, "primaryPosition": {"code": "4", "name": "Second Base", "type": "Infielder", "abbreviation": "2B"}, "useName": "Zack", "useLastName": "Gelof", "middleName": "Dunn", "boxscoreName": "Gelof", "gender": "M", "isPlayer": true, "isVerified": true, "draftYear": 2021, "stats": [{"type": {"displayName": "byDateRange"}, "group": {"displayName": "hitting"}, "exemptions": [], "splits": [{"stat": {"gamesPlayed": 13, "flyOuts": 4, "groundOuts": 15, "airOuts": 7, "runs": 9, "doubles": 2, "triples": 1, "homeRuns": 2, "strikeOuts": 18, "baseOnBalls": 5, "intentionalWalks": 0, "hits": 11, "hitByPitch": 1, "avg": ".220", "atBats": 50, "obp": ".304", "slg": ".420", "ops": ".724", "caughtStealing": 0, "stolenBases": 2, "stolenBasePercentage": "1.000", "groundIntoDoublePlay": 2, "groundIntoTriplePlay": 0, "numberOfPitches": 217, "plateAppearances": 57, "totalBases": 21, "rbi": 5, "leftOnBase": 24, "sacBunts": 1, "sacFlies": 0, "babip": ".300", "groundOutsToAirouts": "2.14", "catchersInterference": 0, "atBatsPerHomeRun": "25.00"}, "team": {"id": 133, "name": "Oakland Athletics", "link": "/api/v1/teams/133"}, "sport": {"id": 1, "link": "/api/v1/sports/1", "abbreviation": "MLB"}, "numTeams": 1, "numLeagues": 13}, {"stat": {"gamesPlayed": 13, "flyOuts": 4, "groundOuts": 15, "airOuts": 7, "runs": 9, "doubles": 2, "triples": 1, "homeRuns": 2, "strikeOuts": 18, "baseOnBalls": 5, "intentionalWalks": 0, "hits": 11, "hitByPitch": 1, "avg": ".220", "atBats": 50, "obp": ".304", "slg": ".420", "ops": ".724", "caughtStealing": 0, "stolenBases": 2, "stolenBasePercentage": "1.000", "groundIntoDoublePlay": 2, "groundIntoTriplePlay": 0, "numberOfPitches": 217, "plateAppearances": 57, "totalBases": 21, "rbi": 5, "leftOnBase": 24, "sacBunts": 1, "sacFlies": 0, "babip": ".300", "groundOutsToAirouts": "2.14", "catchersInterference": 0, "atBatsPerHomeRun": "25.00"}, "team": {"id": 133, "name": "Oakland Athletics", "link": "/api/v1/teams/133"}, "sport": {"id": 0, "link": "/api/v1/sports/0", "abbreviation": "All"}, "numTeams": 1, "numLeagues": 13}]}], "mlbDebutDate": "2023-07-14", "batSide": {"code": "R", "description": "Right"}, "pitchHand": {"code": "R", "description": "Right"}, "nameFirstLast": "Zack Gelof", "nameSlug": "zack-gelof-680869", "firstLastName": "Zack Gelof", "lastFirstName": "Gelof, Zack", "lastInitName": "Gelof, Z", "initLastName": "Z Gelof", "fullFMLName": "Zachary Dunn Gelof", "fullLFMName": "Gelof, Zachary Dunn", "strikeZoneTop": 3.43, "strikeZoneBottom": 1.56}