{"id": 543685, "fullName": "Anthony Rendon", "link": "/api/v1/people/543685", "firstName": "Anthony", "lastName": "Rendon", "primaryNumber": "6", "birthDate": "1990-06-06", "currentAge": 34, "birthCity": "Houston", "birthStateProvince": "TX", "birthCountry": "USA", "height": "6' 1\"", "weight": 200, "active": true, "primaryPosition": {"code": "5", "name": "Third Base", "type": "Infielder", "abbreviation": "3B"}, "useName": "Anthony", "useLastName": "Rendon", "middleName": "Michael", "boxscoreName": "Rendon", "nickName": "Ant", "gender": "M", "isPlayer": true, "isVerified": true, "draftYear": 2011, "pronunciation": "ren-DOHN", "stats": [{"type": {"displayName": "byDateRange"}, "group": {"displayName": "hitting"}, "exemptions": [], "splits": [{"stat": {"gamesPlayed": 18, "flyOuts": 20, "groundOuts": 10, "airOuts": 31, "runs": 9, "doubles": 3, "triples": 0, "homeRuns": 0, "strikeOuts": 15, "baseOnBalls": 6, "intentionalWalks": 0, "hits": 19, "hitByPitch": 1, "avg": ".257", "atBats": 74, "obp": ".317", "slg": ".297", "ops": ".614", "caughtStealing": 1, "stolenBases": 3, "stolenBasePercentage": ".750", "groundIntoDoublePlay": 0, "groundIntoTriplePlay": 0, "numberOfPitches": 361, "plateAppearances": 82, "totalBases": 22, "rbi": 3, "leftOnBase": 23, "sacBunts": 0, "sacFlies": 1, "babip": ".317", "groundOutsToAirouts": "0.32", "catchersInterference": 0, "atBatsPerHomeRun": "-.--"}, "team": {"id": 108, "name": "Los Angeles Angels", "link": "/api/v1/teams/108"}, "sport": {"id": 1, "link": "/api/v1/sports/1", "abbreviation": "MLB"}, "numTeams": 1, "numLeagues": 18}, {"stat": {"gamesPlayed": 18, "flyOuts": 20, "groundOuts": 10, "airOuts": 31, "runs": 9, "doubles": 3, "triples": 0, "homeRuns": 0, "strikeOuts": 15, "baseOnBalls": 6, "intentionalWalks": 0, "hits": 19, "hitByPitch": 1, "avg": ".257", "atBats": 74, "obp": ".317", "slg": ".297", "ops": ".614", "caughtStealing": 1, "stolenBases": 3, "stolenBasePercentage": ".750", "groundIntoDoublePlay": 0, "groundIntoTriplePlay": 0, "numberOfPitches": 361, "plateAppearances": 82, "totalBases": 22, "rbi": 3, "leftOnBase": 23, "sacBunts": 0, "sacFlies": 1, "babip": ".317", "groundOutsToAirouts": "0.32", "catchersInterference": 0, "atBatsPerHomeRun": "-.--"}, "team": {"id": 108, "name": "Los Angeles Angels", "link": "/api/v1/teams/108"}, "sport": {"id": 0, "link": "/api/v1/sports/0", "abbreviation": "All"}, "numTeams": 1, "numLeagues": 18}]}], "mlbDebutDate": "2013-04-21", "batSide": {"code": "R", "description": "Right"}, "pitchHand": {"code": "R", "description": "Right"}, "nameFirstLast": "Anthony Rendon", "nameSlug": "anthony-rendon-543685", "firstLastName": "Anthony Rendon", "lastFirstName": "Rendon, Anthony", "lastInitName": "Rendon, A", "initLastName": "A Rendon", "fullFMLName": "Anthony Michael Rendon", "fullLFMName": "Rendon, Anthony Michael", "strikeZoneTop": 3.38, "strikeZoneBottom": 1.62}