{"id": 691718, "fullName": "Pete Crow-Armstrong", "link": "/api/v1/people/691718", "firstName": "Pete", "lastName": "Crow-Armstrong", "primaryNumber": "52", "birthDate": "2002-03-25", "currentAge": 22, "birthCity": "Sherman Oaks", "birthStateProvince": "CA", "birthCountry": "USA", "height": "5' 11\"", "weight": 184, "active": true, "primaryPosition": {"code": "8", "name": "Outfielder", "type": "Outfielder", "abbreviation": "CF"}, "useName": "Pete", "useLastName": "Crow-Armstrong", "middleName": "Henry", "boxscoreName": "Crow-Armstrong", "nickName": "PCA", "gender": "M", "isPlayer": true, "isVerified": true, "draftYear": 2020, "stats": [{"type": {"displayName": "byDateRange"}, "group": {"displayName": "hitting"}, "exemptions": [], "splits": [{"stat": {"gamesPlayed": 10, "flyOuts": 5, "groundOuts": 9, "airOuts": 8, "runs": 2, "doubles": 2, "triples": 0, "homeRuns": 1, "strikeOuts": 5, "baseOnBalls": 0, "intentionalWalks": 0, "hits": 7, "hitByPitch": 0, "avg": ".259", "atBats": 27, "obp": ".250", "slg": ".444", "ops": ".694", "caughtStealing": 0, "stolenBases": 1, "stolenBasePercentage": "1.000", "groundIntoDoublePlay": 0, "groundIntoTriplePlay": 0, "numberOfPitches": 124, "plateAppearances": 29, "totalBases": 12, "rbi": 7, "leftOnBase": 9, "sacBunts": 1, "sacFlies": 1, "babip": ".273", "groundOutsToAirouts": "1.13", "catchersInterference": 0, "atBatsPerHomeRun": "27.00"}, "team": {"id": 112, "name": "Chicago Cubs", "link": "/api/v1/teams/112"}, "sport": {"id": 1, "link": "/api/v1/sports/1", "abbreviation": "MLB"}, "numTeams": 1, "numLeagues": 10}, {"stat": {"gamesPlayed": 10, "flyOuts": 5, "groundOuts": 9, "airOuts": 8, "runs": 2, "doubles": 2, "triples": 0, "homeRuns": 1, "strikeOuts": 5, "baseOnBalls": 0, "intentionalWalks": 0, "hits": 7, "hitByPitch": 0, "avg": ".259", "atBats": 27, "obp": ".250", "slg": ".444", "ops": ".694", "caughtStealing": 0, "stolenBases": 1, "stolenBasePercentage": "1.000", "groundIntoDoublePlay": 0, "groundIntoTriplePlay": 0, "numberOfPitches": 124, "plateAppearances": 29, "totalBases": 12, "rbi": 7, "leftOnBase": 9, "sacBunts": 1, "sacFlies": 1, "babip": ".273", "groundOutsToAirouts": "1.13", "catchersInterference": 0, "atBatsPerHomeRun": "27.00"}, "team": {"id": 112, "name": "Chicago Cubs", "link": "/api/v1/teams/112"}, "sport": {"id": 0, "link": "/api/v1/sports/0", "abbreviation": "All"}, "numTeams": 1, "numLeagues": 10}]}], "mlbDebutDate": "2023-09-11", "batSide": {"code": "L", "description": "Left"}, "pitchHand": {"code": "L", "description": "Left"}, "nameFirstLast": "Pete Crow-Armstrong", "nameSlug": "pete-crow-armstrong-691718", "firstLastName": "Pete Crow-Armstrong", "lastFirstName": "Crow-Armstrong, Pete", "lastInitName": "Crow-Armstrong, P", "initLastName": "P Crow-Armstrong", "fullFMLName": "Pete Henry Crow-Armstrong", "fullLFMName": "Crow-Armstrong, Pete Henry", "strikeZoneTop": 3.37, "strikeZoneBottom": 1.55}