{"id": 672282, "fullName": "Reid Detmers", "link": "/api/v1/people/672282", "firstName": "Reid", "lastName": "Detmers", "primaryNumber": "48", "birthDate": "1999-07-08", "currentAge": 25, "birthCity": "Nokomis", "birthStateProvince": "IL", "birthCountry": "USA", "height": "6' 2\"", "weight": 210, "active": true, "primaryPosition": {"code": "1", "name": "Pitcher", "type": "Pitcher", "abbreviation": "P"}, "useName": "Reid", "useLastName": "Detmers", "middleName": "Kristien", "boxscoreName": "Detmers", "gender": "M", "isPlayer": true, "isVerified": false, "draftYear": 2020, "stats": [{"type": {"displayName": "byDateRange"}, "group": {"displayName": "pitching"}, "exemptions": [], "splits": [{"stat": {"gamesPlayed": 2, "gamesStarted": 2, "flyOuts": 6, "groundOuts": 6, "airOuts": 7, "runs": 2, "doubles": 1, "triples": 0, "homeRuns": 0, "strikeOuts": 19, "baseOnBalls": 4, "intentionalWalks": 0, "hits": 5, "hitByPitch": 1, "avg": ".135", "atBats": 37, "obp": ".238", "slg": ".162", "ops": ".400", "caughtStealing": 1, "stolenBases": 0, "stolenBasePercentage": ".000", "groundIntoDoublePlay": 0, "numberOfPitches": 182, "era": "1.64", "inningsPitched": "11.0", "wins": 2, "losses": 0, "saves": 0, "saveOpportunities": 0, "holds": 0, "blownSaves": 0, "earnedRuns": 2, "whip": "0.82", "battersFaced": 42, "outs": 33, "gamesPitched": 2, "completeGames": 0, "shutouts": 0, "strikes": 117, "strikePercentage": ".640", "hitBatsmen": 1, "balks": 0, "wildPitches": 0, "pickoffs": 1, "totalBases": 6, "groundOutsToAirouts": "0.86", "winPercentage": "1.000", "pitchesPerInning": "16.55", "gamesFinished": 0, "strikeoutWalkRatio": "4.75", "strikeoutsPer9Inn": "15.55", "walksPer9Inn": "3.27", "hitsPer9Inn": "4.09", "runsScoredPer9": "1.64", "homeRunsPer9": "0.00", "inheritedRunners": 0, "inheritedRunnersScored": 0, "catchersInterference": 0, "sacBunts": 0, "sacFlies": 0}, "team": {"id": 108, "name": "Los Angeles Angels", "link": "/api/v1/teams/108"}, "sport": {"id": 1, "link": "/api/v1/sports/1", "abbreviation": "MLB"}, "numTeams": 1, "numLeagues": 2}, {"stat": {"gamesPlayed": 2, "gamesStarted": 2, "flyOuts": 6, "groundOuts": 6, "airOuts": 7, "runs": 2, "doubles": 1, "triples": 0, "homeRuns": 0, "strikeOuts": 19, "baseOnBalls": 4, "intentionalWalks": 0, "hits": 5, "hitByPitch": 1, "avg": ".135", "atBats": 37, "obp": ".238", "slg": ".162", "ops": ".400", "caughtStealing": 1, "stolenBases": 0, "stolenBasePercentage": ".000", "groundIntoDoublePlay": 0, "numberOfPitches": 182, "era": "1.64", "inningsPitched": "11.0", "wins": 2, "losses": 0, "saves": 0, "saveOpportunities": 0, "holds": 0, "blownSaves": 0, "earnedRuns": 2, "whip": "0.82", "battersFaced": 42, "outs": 33, "gamesPitched": 2, "completeGames": 0, "shutouts": 0, "strikes": 117, "strikePercentage": ".640", "hitBatsmen": 1, "balks": 0, "wildPitches": 0, "pickoffs": 1, "totalBases": 6, "groundOutsToAirouts": "0.86", "winPercentage": "1.000", "pitchesPerInning": "16.55", "gamesFinished": 0, "strikeoutWalkRatio": "4.75", "strikeoutsPer9Inn": "15.55", "walksPer9Inn": "3.27", "hitsPer9Inn": "4.09", "runsScoredPer9": "1.64", "homeRunsPer9": "0.00", "inheritedRunners": 0, "inheritedRunnersScored": 0, "catchersInterference": 0, "sacBunts": 0, "sacFlies": 0}, "team": {"id": 108, "name": "Los Angeles Angels", "link": "/api/v1/teams/108"}, "sport": {"id": 0, "link": "/api/v1/sports/0", "abbreviation": "All"}, "numTeams": 1, "numLeagues": 2}]}], "mlbDebutDate": "2021-08-01", "batSide": {"code": "L", "description": "Left"}, "pitchHand": {"code": "L", "description": "Left"}, "nameFirstLast": "Reid Detmers", "nameSlug": "reid-detmers-672282", "firstLastName": "Reid Detmers", "lastFirstName": "Detmers, Reid", "lastInitName": "Detmers, R", "initLastName": "R Detmers", "fullFMLName": "Reid Kristien Detmers", "fullLFMName": "Detmers, Reid Kristien", "strikeZoneTop": 3.467, "strikeZoneBottom": 1.589}