{"id": 689172, "fullName": "Brett Wisely", "link": "/api/v1/people/689172", "firstName": "Brett", "lastName": "Wisely", "primaryNumber": "0", "birthDate": "1999-05-08", "currentAge": 25, "birthCity": "Jacksonville", "birthStateProvince": "FL", "birthCountry": "USA", "height": "5' 9\"", "weight": 180, "active": true, "primaryPosition": {"code": "4", "name": "Second Base", "type": "Infielder", "abbreviation": "2B"}, "useName": "Brett", "useLastName": "Wisely", "middleName": "Michael", "boxscoreName": "Wisely", "gender": "M", "isPlayer": true, "isVerified": true, "draftYear": 2019, "stats": [{"type": {"displayName": "byDateRange"}, "group": {"displayName": "hitting"}, "exemptions": [], "splits": [{"stat": {"gamesPlayed": 22, "flyOuts": 15, "groundOuts": 11, "airOuts": 18, "runs": 8, "doubles": 3, "triples": 0, "homeRuns": 2, "strikeOuts": 14, "baseOnBalls": 2, "intentionalWalks": 0, "hits": 19, "hitByPitch": 0, "avg": ".311", "atBats": 61, "obp": ".328", "slg": ".459", "ops": ".787", "caughtStealing": 0, "stolenBases": 1, "stolenBasePercentage": "1.000", "groundIntoDoublePlay": 2, "groundIntoTriplePlay": 0, "numberOfPitches": 242, "plateAppearances": 64, "totalBases": 28, "rbi": 9, "leftOnBase": 19, "sacBunts": 0, "sacFlies": 1, "babip": ".370", "groundOutsToAirouts": "0.61", "catchersInterference": 0, "atBatsPerHomeRun": "30.50"}, "team": {"id": 137, "name": "San Francisco Giants", "link": "/api/v1/teams/137"}, "sport": {"id": 1, "link": "/api/v1/sports/1", "abbreviation": "MLB"}, "numTeams": 1, "numLeagues": 22}, {"stat": {"gamesPlayed": 22, "flyOuts": 15, "groundOuts": 11, "airOuts": 18, "runs": 8, "doubles": 3, "triples": 0, "homeRuns": 2, "strikeOuts": 14, "baseOnBalls": 2, "intentionalWalks": 0, "hits": 19, "hitByPitch": 0, "avg": ".311", "atBats": 61, "obp": ".328", "slg": ".459", "ops": ".787", "caughtStealing": 0, "stolenBases": 1, "stolenBasePercentage": "1.000", "groundIntoDoublePlay": 2, "groundIntoTriplePlay": 0, "numberOfPitches": 242, "plateAppearances": 64, "totalBases": 28, "rbi": 9, "leftOnBase": 19, "sacBunts": 0, "sacFlies": 1, "babip": ".370", "groundOutsToAirouts": "0.61", "catchersInterference": 0, "atBatsPerHomeRun": "30.50"}, "team": {"id": 137, "name": "San Francisco Giants", "link": "/api/v1/teams/137"}, "sport": {"id": 0, "link": "/api/v1/sports/0", "abbreviation": "All"}, "numTeams": 1, "numLeagues": 22}]}], "mlbDebutDate": "2023-03-30", "batSide": {"code": "L", "description": "Left"}, "pitchHand": {"code": "R", "description": "Right"}, "nameFirstLast": "Brett Wisely", "nameSlug": "brett-wisely-689172", "firstLastName": "Brett Wisely", "lastFirstName": "Wisely, Brett", "lastInitName": "Wisely, B", "initLastName": "B Wisely", "fullFMLName": "Brett Michael Wisely", "fullLFMName": "Wisely, Brett Michael", "strikeZoneTop": 3.37, "strikeZoneBottom": 1.57}