{"id": 572233, "fullName": "Christian Walker", "link": "/api/v1/people/572233", "firstName": "Christian", "lastName": "Walker", "primaryNumber": "53", "birthDate": "1991-03-28", "currentAge": 33, "birthCity": "Norristown", "birthStateProvince": "PA", "birthCountry": "USA", "height": "6' 0\"", "weight": 208, "active": true, "primaryPosition": {"code": "3", "name": "First Base", "type": "Infielder", "abbreviation": "1B"}, "useName": "Christian", "useLastName": "Walker", "middleName": "Dickson", "boxscoreName": "Walker, C", "nickName": "C. Walk", "gender": "M", "isPlayer": true, "isVerified": true, "draftYear": 2012, "stats": [{"type": {"displayName": "byDateRange"}, "group": {"displayName": "hitting"}, "exemptions": [], "splits": [{"stat": {"gamesPlayed": 32, "flyOuts": 18, "groundOuts": 25, "airOuts": 28, "runs": 24, "doubles": 3, "triples": 0, "homeRuns": 7, "strikeOuts": 33, "baseOnBalls": 21, "intentionalWalks": 0, "hits": 32, "hitByPitch": 2, "avg": ".276", "atBats": 116, "obp": ".390", "slg": ".483", "ops": ".873", "caughtStealing": 2, "stolenBases": 0, "stolenBasePercentage": ".000", "groundIntoDoublePlay": 4, "groundIntoTriplePlay": 0, "numberOfPitches": 603, "plateAppearances": 141, "totalBases": 56, "rbi": 22, "leftOnBase": 59, "sacBunts": 0, "sacFlies": 2, "babip": ".321", "groundOutsToAirouts": "0.89", "catchersInterference": 0, "atBatsPerHomeRun": "16.57"}, "team": {"id": 109, "name": "Arizona Diamondbacks", "link": "/api/v1/teams/109"}, "sport": {"id": 1, "link": "/api/v1/sports/1", "abbreviation": "MLB"}, "numTeams": 1, "numLeagues": 32}, {"stat": {"gamesPlayed": 32, "flyOuts": 18, "groundOuts": 25, "airOuts": 28, "runs": 24, "doubles": 3, "triples": 0, "homeRuns": 7, "strikeOuts": 33, "baseOnBalls": 21, "intentionalWalks": 0, "hits": 32, "hitByPitch": 2, "avg": ".276", "atBats": 116, "obp": ".390", "slg": ".483", "ops": ".873", "caughtStealing": 2, "stolenBases": 0, "stolenBasePercentage": ".000", "groundIntoDoublePlay": 4, "groundIntoTriplePlay": 0, "numberOfPitches": 603, "plateAppearances": 141, "totalBases": 56, "rbi": 22, "leftOnBase": 59, "sacBunts": 0, "sacFlies": 2, "babip": ".321", "groundOutsToAirouts": "0.89", "catchersInterference": 0, "atBatsPerHomeRun": "16.57"}, "team": {"id": 109, "name": "Arizona Diamondbacks", "link": "/api/v1/teams/109"}, "sport": {"id": 0, "link": "/api/v1/sports/0", "abbreviation": "All"}, "numTeams": 1, "numLeagues": 32}]}], "mlbDebutDate": "2014-09-17", "batSide": {"code": "R", "description": "Right"}, "pitchHand": {"code": "R", "description": "Right"}, "nameFirstLast": "Christian Walker", "nameSlug": "christian-walker-572233", "firstLastName": "Christian Walker", "lastFirstName": "Walker, Christian", "lastInitName": "Walker, C", "initLastName": "C Walker", "fullFMLName": "Christian Dickson Walker", "fullLFMName": "Walker, Christian Dickson", "strikeZoneTop": 3.42, "strikeZoneBottom": 1.53}