{"id": 663728, "fullName": "Cal Raleigh", "link": "/api/v1/people/663728", "firstName": "Caleb", "lastName": "Raleigh", "primaryNumber": "29", "birthDate": "1996-11-26", "currentAge": 27, "birthCity": "Cullowhee", "birthStateProvince": "NC", "birthCountry": "USA", "height": "6' 3\"", "weight": 235, "active": true, "primaryPosition": {"code": "2", "name": "Catcher", "type": "Catcher", "abbreviation": "C"}, "useName": "Cal", "useLastName": "Raleigh", "middleName": "John", "boxscoreName": "Raleigh", "gender": "M", "isPlayer": true, "isVerified": true, "draftYear": 2018, "stats": [{"type": {"displayName": "byDateRange"}, "group": {"displayName": "hitting"}, "exemptions": [], "splits": [{"stat": {"gamesPlayed": 27, "flyOuts": 12, "groundOuts": 16, "airOuts": 20, "runs": 12, "doubles": 0, "triples": 0, "homeRuns": 6, "strikeOuts": 37, "baseOnBalls": 12, "intentionalWalks": 0, "hits": 20, "hitByPitch": 0, "avg": ".217", "atBats": 92, "obp": ".305", "slg": ".413", "ops": ".718", "caughtStealing": 0, "stolenBases": 0, "stolenBasePercentage": ".---", "groundIntoDoublePlay": 1, "groundIntoTriplePlay": 0, "numberOfPitches": 438, "plateAppearances": 105, "totalBases": 38, "rbi": 13, "leftOnBase": 43, "sacBunts": 0, "sacFlies": 1, "babip": ".280", "groundOutsToAirouts": "0.80", "catchersInterference": 0, "atBatsPerHomeRun": "15.33"}, "team": {"id": 136, "name": "Seattle Mariners", "link": "/api/v1/teams/136"}, "sport": {"id": 1, "link": "/api/v1/sports/1", "abbreviation": "MLB"}, "numTeams": 1, "numLeagues": 27}, {"stat": {"gamesPlayed": 27, "flyOuts": 12, "groundOuts": 16, "airOuts": 20, "runs": 12, "doubles": 0, "triples": 0, "homeRuns": 6, "strikeOuts": 37, "baseOnBalls": 12, "intentionalWalks": 0, "hits": 20, "hitByPitch": 0, "avg": ".217", "atBats": 92, "obp": ".305", "slg": ".413", "ops": ".718", "caughtStealing": 0, "stolenBases": 0, "stolenBasePercentage": ".---", "groundIntoDoublePlay": 1, "groundIntoTriplePlay": 0, "numberOfPitches": 438, "plateAppearances": 105, "totalBases": 38, "rbi": 13, "leftOnBase": 43, "sacBunts": 0, "sacFlies": 1, "babip": ".280", "groundOutsToAirouts": "0.80", "catchersInterference": 0, "atBatsPerHomeRun": "15.33"}, "team": {"id": 136, "name": "Seattle Mariners", "link": "/api/v1/teams/136"}, "sport": {"id": 0, "link": "/api/v1/sports/0", "abbreviation": "All"}, "numTeams": 1, "numLeagues": 27}]}], "mlbDebutDate": "2021-07-11", "batSide": {"code": "S", "description": "Switch"}, "pitchHand": {"code": "R", "description": "Right"}, "nameFirstLast": "Cal Raleigh", "nameSlug": "cal-raleigh-663728", "firstLastName": "Cal Raleigh", "lastFirstName": "Raleigh, Cal", "lastInitName": "Raleigh, C", "initLastName": "C Raleigh", "fullFMLName": "Caleb John Raleigh", "fullLFMName": "Raleigh, Caleb John", "strikeZoneTop": 3.49, "strikeZoneBottom": 1.61}