{"id": 641540, "fullName": "Dane Dunning", "link": "/api/v1/people/641540", "firstName": "Dane", "lastName": "Dunning", "primaryNumber": "33", "birthDate": "1994-12-20", "currentAge": 29, "birthCity": "Orange Park", "birthStateProvince": "FL", "birthCountry": "USA", "height": "6' 4\"", "weight": 225, "active": true, "primaryPosition": {"code": "1", "name": "Pitcher", "type": "Pitcher", "abbreviation": "P"}, "useName": "Dane", "useLastName": "Dunning", "middleName": "Anthony", "boxscoreName": "Dunning", "gender": "M", "isPlayer": true, "isVerified": false, "draftYear": 2016, "stats": [{"type": {"displayName": "byDateRange"}, "group": {"displayName": "pitching"}, "exemptions": [], "splits": [{"stat": {"gamesPlayed": 3, "gamesStarted": 3, "flyOuts": 11, "groundOuts": 16, "airOuts": 18, "runs": 9, "doubles": 1, "triples": 0, "homeRuns": 4, "strikeOuts": 17, "baseOnBalls": 9, "intentionalWalks": 0, "hits": 12, "hitByPitch": 3, "avg": ".190", "atBats": 63, "obp": ".320", "slg": ".397", "ops": ".717", "caughtStealing": 1, "stolenBases": 2, "stolenBasePercentage": ".667", "groundIntoDoublePlay": 2, "numberOfPitches": 270, "era": "4.50", "inningsPitched": "18.0", "wins": 2, "losses": 1, "saves": 0, "saveOpportunities": 0, "holds": 0, "blownSaves": 0, "earnedRuns": 9, "whip": "1.17", "battersFaced": 75, "outs": 54, "gamesPitched": 3, "completeGames": 0, "shutouts": 0, "strikes": 164, "strikePercentage": ".610", "hitBatsmen": 3, "balks": 0, "wildPitches": 0, "pickoffs": 0, "totalBases": 25, "groundOutsToAirouts": "0.89", "winPercentage": ".667", "pitchesPerInning": "15.00", "gamesFinished": 0, "strikeoutWalkRatio": "1.89", "strikeoutsPer9Inn": "8.50", "walksPer9Inn": "4.50", "hitsPer9Inn": "6.00", "runsScoredPer9": "4.50", "homeRunsPer9": "2.00", "inheritedRunners": 0, "inheritedRunnersScored": 0, "catchersInterference": 0, "sacBunts": 0, "sacFlies": 0}, "team": {"id": 140, "name": "Texas Rangers", "link": "/api/v1/teams/140"}, "sport": {"id": 1, "link": "/api/v1/sports/1", "abbreviation": "MLB"}, "numTeams": 1, "numLeagues": 3}, {"stat": {"gamesPlayed": 3, "gamesStarted": 3, "flyOuts": 11, "groundOuts": 16, "airOuts": 18, "runs": 9, "doubles": 1, "triples": 0, "homeRuns": 4, "strikeOuts": 17, "baseOnBalls": 9, "intentionalWalks": 0, "hits": 12, "hitByPitch": 3, "avg": ".190", "atBats": 63, "obp": ".320", "slg": ".397", "ops": ".717", "caughtStealing": 1, "stolenBases": 2, "stolenBasePercentage": ".667", "groundIntoDoublePlay": 2, "numberOfPitches": 270, "era": "4.50", "inningsPitched": "18.0", "wins": 2, "losses": 1, "saves": 0, "saveOpportunities": 0, "holds": 0, "blownSaves": 0, "earnedRuns": 9, "whip": "1.17", "battersFaced": 75, "outs": 54, "gamesPitched": 3, "completeGames": 0, "shutouts": 0, "strikes": 164, "strikePercentage": ".610", "hitBatsmen": 3, "balks": 0, "wildPitches": 0, "pickoffs": 0, "totalBases": 25, "groundOutsToAirouts": "0.89", "winPercentage": ".667", "pitchesPerInning": "15.00", "gamesFinished": 0, "strikeoutWalkRatio": "1.89", "strikeoutsPer9Inn": "8.50", "walksPer9Inn": "4.50", "hitsPer9Inn": "6.00", "runsScoredPer9": "4.50", "homeRunsPer9": "2.00", "inheritedRunners": 0, "inheritedRunnersScored": 0, "catchersInterference": 0, "sacBunts": 0, "sacFlies": 0}, "team": {"id": 140, "name": "Texas Rangers", "link": "/api/v1/teams/140"}, "sport": {"id": 0, "link": "/api/v1/sports/0", "abbreviation": "All"}, "numTeams": 1, "numLeagues": 3}]}], "mlbDebutDate": "2020-08-19", "batSide": {"code": "R", "description": "Right"}, "pitchHand": {"code": "R", "description": "Right"}, "nameFirstLast": "Dane Dunning", "nameSlug": "dane-dunning-641540", "firstLastName": "Dane Dunning", "lastFirstName": "Dunning, Dane", "lastInitName": "Dunning, D", "initLastName": "D Dunning", "fullFMLName": "Dane Anthony Dunning", "fullLFMName": "Dunning, Dane Anthony", "strikeZoneTop": 3.549, "strikeZoneBottom": 1.627}