{"id": 514888, "fullName": "Jose Altuve", "link": "/api/v1/people/514888", "firstName": "Jose", "lastName": "Altuve", "primaryNumber": "27", "birthDate": "1990-05-06", "currentAge": 34, "birthCity": "Maracay", "birthCountry": "Venezuela", "height": "5' 6\"", "weight": 167, "active": true, "primaryPosition": {"code": "4", "name": "Second Base", "type": "Infielder", "abbreviation": "2B"}, "useName": "Jose", "useLastName": "Altuve", "middleName": "Carlos", "boxscoreName": "Altuve", "nickName": "Tuve", "gender": "M", "isPlayer": true, "isVerified": true, "pronunciation": "al-TOO-vay", "stats": [{"type": {"displayName": "byDateRange"}, "group": {"displayName": "hitting"}, "exemptions": [], "splits": [{"stat": {"gamesPlayed": 62, "flyOuts": 44, "groundOuts": 56, "airOuts": 75, "runs": 35, "doubles": 12, "triples": 0, "homeRuns": 9, "strikeOuts": 50, "baseOnBalls": 18, "intentionalWalks": 1, "hits": 73, "hitByPitch": 3, "avg": ".287", "atBats": 254, "obp": ".342", "slg": ".441", "ops": ".783", "caughtStealing": 3, "stolenBases": 8, "stolenBasePercentage": ".727", "groundIntoDoublePlay": 6, "groundIntoTriplePlay": 0, "numberOfPitches": 1007, "plateAppearances": 275, "totalBases": 112, "rbi": 21, "leftOnBase": 74, "sacBunts": 0, "sacFlies": 0, "babip": ".328", "groundOutsToAirouts": "0.75", "catchersInterference": 0, "atBatsPerHomeRun": "28.22"}, "team": {"id": 117, "name": "Houston Astros", "link": "/api/v1/teams/117"}, "sport": {"id": 1, "link": "/api/v1/sports/1", "abbreviation": "MLB"}, "numTeams": 1, "numLeagues": 62}, {"stat": {"gamesPlayed": 62, "flyOuts": 44, "groundOuts": 56, "airOuts": 75, "runs": 35, "doubles": 12, "triples": 0, "homeRuns": 9, "strikeOuts": 50, "baseOnBalls": 18, "intentionalWalks": 1, "hits": 73, "hitByPitch": 3, "avg": ".287", "atBats": 254, "obp": ".342", "slg": ".441", "ops": ".783", "caughtStealing": 3, "stolenBases": 8, "stolenBasePercentage": ".727", "groundIntoDoublePlay": 6, "groundIntoTriplePlay": 0, "numberOfPitches": 1007, "plateAppearances": 275, "totalBases": 112, "rbi": 21, "leftOnBase": 74, "sacBunts": 0, "sacFlies": 0, "babip": ".328", "groundOutsToAirouts": "0.75", "catchersInterference": 0, "atBatsPerHomeRun": "28.22"}, "team": {"id": 117, "name": "Houston Astros", "link": "/api/v1/teams/117"}, "sport": {"id": 0, "link": "/api/v1/sports/0", "abbreviation": "All"}, "numTeams": 1, "numLeagues": 62}]}], "mlbDebutDate": "2011-07-20", "batSide": {"code": "R", "description": "Right"}, "pitchHand": {"code": "R", "description": "Right"}, "nameFirstLast": "Jose Altuve", "nameSlug": "jose-altuve-514888", "firstLastName": "Jose Altuve", "lastFirstName": "Altuve, Jose", "lastInitName": "Altuve, J", "initLastName": "J Altuve", "fullFMLName": "Jose Carlos Altuve", "fullLFMName": "Altuve, Jose Carlos", "strikeZoneTop": 2.89, "strikeZoneBottom": 1.31}