{"id": 656302, "fullName": "Dylan Cease", "link": "/api/v1/people/656302", "firstName": "Dylan", "lastName": "Cease", "primaryNumber": "84", "birthDate": "1995-12-28", "currentAge": 28, "birthCity": "Milton", "birthStateProvince": "GA", "birthCountry": "USA", "height": "6' 2\"", "weight": 200, "active": true, "primaryPosition": {"code": "1", "name": "Pitcher", "type": "Pitcher", "abbreviation": "P"}, "useName": "Dylan", "useLastName": "Cease", "middleName": "Edward", "boxscoreName": "Cease", "nickName": "Cease", "gender": "M", "isPlayer": true, "isVerified": true, "draftYear": 2014, "stats": [{"type": {"displayName": "byDateRange"}, "group": {"displayName": "pitching"}, "exemptions": [], "splits": [{"stat": {"gamesPlayed": 10, "gamesStarted": 10, "flyOuts": 40, "groundOuts": 39, "airOuts": 64, "runs": 23, "doubles": 10, "triples": 0, "homeRuns": 5, "strikeOuts": 73, "baseOnBalls": 20, "intentionalWalks": 0, "hits": 35, "hitByPitch": 1, "avg": ".169", "atBats": 207, "obp": ".242", "slg": ".290", "ops": ".532", "caughtStealing": 0, "stolenBases": 0, "stolenBasePercentage": ".---", "groundIntoDoublePlay": 4, "numberOfPitches": 981, "era": "3.05", "inningsPitched": "59.0", "wins": 5, "losses": 3, "saves": 0, "saveOpportunities": 0, "holds": 0, "blownSaves": 0, "earnedRuns": 20, "whip": "0.93", "battersFaced": 233, "outs": 177, "gamesPitched": 10, "completeGames": 0, "shutouts": 0, "strikes": 609, "strikePercentage": ".620", "hitBatsmen": 1, "balks": 0, "wildPitches": 2, "pickoffs": 0, "totalBases": 60, "groundOutsToAirouts": "0.61", "winPercentage": ".625", "pitchesPerInning": "16.63", "gamesFinished": 0, "strikeoutWalkRatio": "3.65", "strikeoutsPer9Inn": "11.14", "walksPer9Inn": "3.05", "hitsPer9Inn": "5.34", "runsScoredPer9": "3.51", "homeRunsPer9": "0.76", "inheritedRunners": 0, "inheritedRunnersScored": 0, "catchersInterference": 1, "sacBunts": 1, "sacFlies": 3}, "team": {"id": 135, "name": "San Diego Padres", "link": "/api/v1/teams/135"}, "sport": {"id": 1, "link": "/api/v1/sports/1", "abbreviation": "MLB"}, "numTeams": 1, "numLeagues": 10}, {"stat": {"gamesPlayed": 10, "gamesStarted": 10, "flyOuts": 40, "groundOuts": 39, "airOuts": 64, "runs": 23, "doubles": 10, "triples": 0, "homeRuns": 5, "strikeOuts": 73, "baseOnBalls": 20, "intentionalWalks": 0, "hits": 35, "hitByPitch": 1, "avg": ".169", "atBats": 207, "obp": ".242", "slg": ".290", "ops": ".532", "caughtStealing": 0, "stolenBases": 0, "stolenBasePercentage": ".---", "groundIntoDoublePlay": 4, "numberOfPitches": 981, "era": "3.05", "inningsPitched": "59.0", "wins": 5, "losses": 3, "saves": 0, "saveOpportunities": 0, "holds": 0, "blownSaves": 0, "earnedRuns": 20, "whip": "0.93", "battersFaced": 233, "outs": 177, "gamesPitched": 10, "completeGames": 0, "shutouts": 0, "strikes": 609, "strikePercentage": ".620", "hitBatsmen": 1, "balks": 0, "wildPitches": 2, "pickoffs": 0, "totalBases": 60, "groundOutsToAirouts": "0.61", "winPercentage": ".625", "pitchesPerInning": "16.63", "gamesFinished": 0, "strikeoutWalkRatio": "3.65", "strikeoutsPer9Inn": "11.14", "walksPer9Inn": "3.05", "hitsPer9Inn": "5.34", "runsScoredPer9": "3.51", "homeRunsPer9": "0.76", "inheritedRunners": 0, "inheritedRunnersScored": 0, "catchersInterference": 1, "sacBunts": 1, "sacFlies": 3}, "team": {"id": 135, "name": "San Diego Padres", "link": "/api/v1/teams/135"}, "sport": {"id": 0, "link": "/api/v1/sports/0", "abbreviation": "All"}, "numTeams": 1, "numLeagues": 10}]}], "mlbDebutDate": "2019-07-03", "batSide": {"code": "R", "description": "Right"}, "pitchHand": {"code": "R", "description": "Right"}, "nameFirstLast": "Dylan Cease", "nameSlug": "dylan-cease-656302", "firstLastName": "Dylan Cease", "lastFirstName": "Cease, Dylan", "lastInitName": "Cease, D", "initLastName": "D Cease", "fullFMLName": "Dylan Edward Cease", "fullLFMName": "Cease, Dylan Edward", "strikeZoneTop": 3.467, "strikeZoneBottom": 1.589}