{"id": 663903, "fullName": "Brady Singer", "link": "/api/v1/people/663903", "firstName": "Brady", "lastName": "Singer", "primaryNumber": "51", "birthDate": "1996-08-04", "currentAge": 28, "birthCity": "Leesburg", "birthStateProvince": "FL", "birthCountry": "USA", "height": "6' 5\"", "weight": 215, "active": true, "primaryPosition": {"code": "1", "name": "Pitcher", "type": "Pitcher", "abbreviation": "P"}, "useName": "Brady", "useLastName": "Singer", "middleName": "Alan", "boxscoreName": "Singer", "gender": "M", "isPlayer": true, "isVerified": true, "draftYear": 2018, "stats": [{"type": {"displayName": "byDateRange"}, "group": {"displayName": "pitching"}, "exemptions": [], "splits": [{"stat": {"gamesPlayed": 10, "gamesStarted": 10, "flyOuts": 23, "groundOuts": 66, "airOuts": 41, "runs": 17, "doubles": 13, "triples": 2, "homeRuns": 5, "strikeOuts": 61, "baseOnBalls": 17, "intentionalWalks": 0, "hits": 46, "hitByPitch": 3, "avg": ".216", "atBats": 213, "obp": ".283", "slg": ".366", "ops": ".649", "caughtStealing": 0, "stolenBases": 0, "stolenBasePercentage": ".---", "groundIntoDoublePlay": 3, "numberOfPitches": 941, "era": "2.70", "inningsPitched": "56.2", "wins": 4, "losses": 2, "saves": 0, "saveOpportunities": 0, "holds": 0, "blownSaves": 0, "earnedRuns": 17, "whip": "1.11", "battersFaced": 234, "outs": 170, "gamesPitched": 10, "completeGames": 0, "shutouts": 0, "strikes": 602, "strikePercentage": ".640", "hitBatsmen": 3, "balks": 0, "wildPitches": 0, "pickoffs": 0, "totalBases": 78, "groundOutsToAirouts": "1.61", "winPercentage": ".667", "pitchesPerInning": "16.61", "gamesFinished": 0, "strikeoutWalkRatio": "3.59", "strikeoutsPer9Inn": "9.69", "walksPer9Inn": "2.70", "hitsPer9Inn": "7.31", "runsScoredPer9": "2.70", "homeRunsPer9": "0.79", "inheritedRunners": 0, "inheritedRunnersScored": 0, "catchersInterference": 0, "sacBunts": 1, "sacFlies": 0}, "team": {"id": 118, "name": "Kansas City Royals", "link": "/api/v1/teams/118"}, "sport": {"id": 1, "link": "/api/v1/sports/1", "abbreviation": "MLB"}, "numTeams": 1, "numLeagues": 10}, {"stat": {"gamesPlayed": 10, "gamesStarted": 10, "flyOuts": 23, "groundOuts": 66, "airOuts": 41, "runs": 17, "doubles": 13, "triples": 2, "homeRuns": 5, "strikeOuts": 61, "baseOnBalls": 17, "intentionalWalks": 0, "hits": 46, "hitByPitch": 3, "avg": ".216", "atBats": 213, "obp": ".283", "slg": ".366", "ops": ".649", "caughtStealing": 0, "stolenBases": 0, "stolenBasePercentage": ".---", "groundIntoDoublePlay": 3, "numberOfPitches": 941, "era": "2.70", "inningsPitched": "56.2", "wins": 4, "losses": 2, "saves": 0, "saveOpportunities": 0, "holds": 0, "blownSaves": 0, "earnedRuns": 17, "whip": "1.11", "battersFaced": 234, "outs": 170, "gamesPitched": 10, "completeGames": 0, "shutouts": 0, "strikes": 602, "strikePercentage": ".640", "hitBatsmen": 3, "balks": 0, "wildPitches": 0, "pickoffs": 0, "totalBases": 78, "groundOutsToAirouts": "1.61", "winPercentage": ".667", "pitchesPerInning": "16.61", "gamesFinished": 0, "strikeoutWalkRatio": "3.59", "strikeoutsPer9Inn": "9.69", "walksPer9Inn": "2.70", "hitsPer9Inn": "7.31", "runsScoredPer9": "2.70", "homeRunsPer9": "0.79", "inheritedRunners": 0, "inheritedRunnersScored": 0, "catchersInterference": 0, "sacBunts": 1, "sacFlies": 0}, "team": {"id": 118, "name": "Kansas City Royals", "link": "/api/v1/teams/118"}, "sport": {"id": 0, "link": "/api/v1/sports/0", "abbreviation": "All"}, "numTeams": 1, "numLeagues": 10}]}], "mlbDebutDate": "2020-07-25", "batSide": {"code": "R", "description": "Right"}, "pitchHand": {"code": "R", "description": "Right"}, "nameFirstLast": "Brady Singer", "nameSlug": "brady-singer-663903", "firstLastName": "Brady Singer", "lastFirstName": "Singer, Brady", "lastInitName": "Singer, B", "initLastName": "B Singer", "fullFMLName": "Brady Alan Singer", "fullLFMName": "Singer, Brady Alan", "strikeZoneTop": 3.575, "strikeZoneBottom": 1.681}