{"id": 516782, "fullName": "Starling Marte", "link": "/api/v1/people/516782", "firstName": "Starling", "lastName": "Marte", "primaryNumber": "6", "birthDate": "1988-10-09", "currentAge": 36, "birthCity": "Santo Domingo", "birthCountry": "Dominican Republic", "height": "6' 1\"", "weight": 195, "active": true, "primaryPosition": {"code": "9", "name": "Outfielder", "type": "Outfielder", "abbreviation": "RF"}, "useName": "Starling", "useLastName": "Marte", "middleName": "Javier", "boxscoreName": "Marte, S", "nickName": "Tato", "gender": "M", "isPlayer": true, "isVerified": true, "pronunciation": "mar-TAY", "stats": [{"type": {"displayName": "byDateRange"}, "group": {"displayName": "hitting"}, "exemptions": [], "splits": [{"stat": {"gamesPlayed": 15, "flyOuts": 7, "groundOuts": 20, "airOuts": 12, "runs": 10, "doubles": 1, "triples": 0, "homeRuns": 2, "strikeOuts": 13, "baseOnBalls": 6, "intentionalWalks": 0, "hits": 17, "hitByPitch": 0, "avg": ".279", "atBats": 61, "obp": ".343", "slg": ".393", "ops": ".736", "caughtStealing": 0, "stolenBases": 3, "stolenBasePercentage": "1.000", "groundIntoDoublePlay": 1, "groundIntoTriplePlay": 0, "numberOfPitches": 259, "plateAppearances": 68, "totalBases": 24, "rbi": 4, "leftOnBase": 23, "sacBunts": 1, "sacFlies": 0, "babip": ".326", "groundOutsToAirouts": "1.67", "catchersInterference": 0, "atBatsPerHomeRun": "30.50"}, "team": {"id": 121, "name": "New York Mets", "link": "/api/v1/teams/121"}, "sport": {"id": 1, "link": "/api/v1/sports/1", "abbreviation": "MLB"}, "numTeams": 1, "numLeagues": 15}, {"stat": {"gamesPlayed": 15, "flyOuts": 7, "groundOuts": 20, "airOuts": 12, "runs": 10, "doubles": 1, "triples": 0, "homeRuns": 2, "strikeOuts": 13, "baseOnBalls": 6, "intentionalWalks": 0, "hits": 17, "hitByPitch": 0, "avg": ".279", "atBats": 61, "obp": ".343", "slg": ".393", "ops": ".736", "caughtStealing": 0, "stolenBases": 3, "stolenBasePercentage": "1.000", "groundIntoDoublePlay": 1, "groundIntoTriplePlay": 0, "numberOfPitches": 259, "plateAppearances": 68, "totalBases": 24, "rbi": 4, "leftOnBase": 23, "sacBunts": 1, "sacFlies": 0, "babip": ".326", "groundOutsToAirouts": "1.67", "catchersInterference": 0, "atBatsPerHomeRun": "30.50"}, "team": {"id": 121, "name": "New York Mets", "link": "/api/v1/teams/121"}, "sport": {"id": 0, "link": "/api/v1/sports/0", "abbreviation": "All"}, "numTeams": 1, "numLeagues": 15}]}], "mlbDebutDate": "2012-07-26", "batSide": {"code": "R", "description": "Right"}, "pitchHand": {"code": "R", "description": "Right"}, "nameFirstLast": "Starling Marte", "nameSlug": "starling-marte-516782", "firstLastName": "Starling Marte", "lastFirstName": "Marte, Starling", "lastInitName": "Marte, S", "initLastName": "S Marte", "fullFMLName": "Starling Javier Marte", "fullLFMName": "Marte, Starling Javier", "strikeZoneTop": 3.5, "strikeZoneBottom": 1.62}