{"id": 696131, "fullName": "Mason Black", "link": "/api/v1/people/696131", "firstName": "Mason", "lastName": "Black", "primaryNumber": "47", "birthDate": "1999-12-10", "currentAge": 24, "birthCity": "Scranton", "birthStateProvince": "PA", "birthCountry": "USA", "height": "6' 3\"", "weight": 230, "active": true, "primaryPosition": {"code": "1", "name": "Pitcher", "type": "Pitcher", "abbreviation": "P"}, "useName": "Mason", "useLastName": "Black", "middleName": "Peter", "boxscoreName": "Black", "gender": "M", "isPlayer": true, "isVerified": true, "draftYear": 2021, "stats": [{"type": {"displayName": "byDateRange"}, "group": {"displayName": "pitching"}, "exemptions": [], "splits": [{"stat": {"gamesPlayed": 2, "gamesStarted": 2, "flyOuts": 8, "groundOuts": 6, "airOuts": 12, "runs": 6, "doubles": 3, "triples": 0, "homeRuns": 2, "strikeOuts": 6, "baseOnBalls": 5, "intentionalWalks": 0, "hits": 12, "hitByPitch": 1, "avg": ".333", "atBats": 36, "obp": ".429", "slg": ".583", "ops": "1.012", "caughtStealing": 0, "stolenBases": 2, "stolenBasePercentage": "1.000", "groundIntoDoublePlay": 0, "numberOfPitches": 162, "era": "6.23", "inningsPitched": "8.2", "wins": 0, "losses": 1, "saves": 0, "saveOpportunities": 0, "holds": 0, "blownSaves": 0, "earnedRuns": 6, "whip": "1.96", "battersFaced": 42, "outs": 26, "gamesPitched": 2, "completeGames": 0, "shutouts": 0, "strikes": 102, "strikePercentage": ".630", "hitBatsmen": 1, "balks": 0, "wildPitches": 0, "pickoffs": 0, "totalBases": 21, "groundOutsToAirouts": "0.50", "winPercentage": ".000", "pitchesPerInning": "18.69", "gamesFinished": 0, "strikeoutWalkRatio": "1.20", "strikeoutsPer9Inn": "6.23", "walksPer9Inn": "5.19", "hitsPer9Inn": "12.46", "runsScoredPer9": "6.23", "homeRunsPer9": "2.08", "inheritedRunners": 0, "inheritedRunnersScored": 0, "catchersInterference": 0, "sacBunts": 0, "sacFlies": 0}, "team": {"id": 137, "name": "San Francisco Giants", "link": "/api/v1/teams/137"}, "sport": {"id": 1, "link": "/api/v1/sports/1", "abbreviation": "MLB"}, "numTeams": 1, "numLeagues": 2}, {"stat": {"gamesPlayed": 2, "gamesStarted": 2, "flyOuts": 8, "groundOuts": 6, "airOuts": 12, "runs": 6, "doubles": 3, "triples": 0, "homeRuns": 2, "strikeOuts": 6, "baseOnBalls": 5, "intentionalWalks": 0, "hits": 12, "hitByPitch": 1, "avg": ".333", "atBats": 36, "obp": ".429", "slg": ".583", "ops": "1.012", "caughtStealing": 0, "stolenBases": 2, "stolenBasePercentage": "1.000", "groundIntoDoublePlay": 0, "numberOfPitches": 162, "era": "6.23", "inningsPitched": "8.2", "wins": 0, "losses": 1, "saves": 0, "saveOpportunities": 0, "holds": 0, "blownSaves": 0, "earnedRuns": 6, "whip": "1.96", "battersFaced": 42, "outs": 26, "gamesPitched": 2, "completeGames": 0, "shutouts": 0, "strikes": 102, "strikePercentage": ".630", "hitBatsmen": 1, "balks": 0, "wildPitches": 0, "pickoffs": 0, "totalBases": 21, "groundOutsToAirouts": "0.50", "winPercentage": ".000", "pitchesPerInning": "18.69", "gamesFinished": 0, "strikeoutWalkRatio": "1.20", "strikeoutsPer9Inn": "6.23", "walksPer9Inn": "5.19", "hitsPer9Inn": "12.46", "runsScoredPer9": "6.23", "homeRunsPer9": "2.08", "inheritedRunners": 0, "inheritedRunnersScored": 0, "catchersInterference": 0, "sacBunts": 0, "sacFlies": 0}, "team": {"id": 137, "name": "San Francisco Giants", "link": "/api/v1/teams/137"}, "sport": {"id": 0, "link": "/api/v1/sports/0", "abbreviation": "All"}, "numTeams": 1, "numLeagues": 2}]}], "mlbDebutDate": "2024-05-06", "batSide": {"code": "R", "description": "Right"}, "pitchHand": {"code": "R", "description": "Right"}, "nameFirstLast": "Mason Black", "nameSlug": "mason-black-696131", "firstLastName": "Mason Black", "lastFirstName": "Black, Mason", "lastInitName": "Black, M", "initLastName": "M Black", "fullFMLName": "Mason Peter Black", "fullLFMName": "Black, Mason Peter", "strikeZoneTop": 3.49, "strikeZoneBottom": 1.601}