[{"game_id": 746783, "game_datetime": "2024-06-19T00:10:00Z", "game_date": "2024-06-18", "game_type": "R", "status": "Final", "away_name": "Houston Astros", "home_name": "Chicago White Sox", "away_id": 117, "home_id": 145, "doubleheader": "N", "game_num": 1, "home_probable_pitcher": "Jonathan Cannon", "away_probable_pitcher": "Framber Valdez", "home_pitcher_note": "", "away_pitcher_note": "", "away_score": 0, "home_score": 2, "current_inning": 9, "inning_state": "Top", "venue_id": 4, "venue_name": "Guaranteed Rate Field", "national_broadcasts": [], "series_status": null, "winning_team": "Chicago White Sox", "losing_team": "Houston Astros", "winning_pitcher": "Jonathan Cannon", "losing_pitcher": "Framber Valdez", "save_pitcher": "John Brebbia", "summary": "2024-06-18 - Houston Astros (0) @ Chicago White Sox (2) (Final)"}]